simpledit/SimplEdit
simpledit/__init__.py
simpledit/gui.py
simpledit/im_functions.py
simpledit/image.py
simpledit/main.py
simpledit/images/Crop.svg
simpledit/images/Custom.svg
simpledit/images/add_filter.svg
simpledit/images/aqua.png
simpledit/images/before_after.svg
simpledit/images/blur.svg
simpledit/images/border.svg
simpledit/images/brightness.svg
simpledit/images/contrast.png
simpledit/images/default.png
simpledit/images/demo.png
simpledit/images/enhance.svg
simpledit/images/flip.png
simpledit/images/grayscale.svg
simpledit/images/invert.svg
simpledit/images/jovic.png
simpledit/images/loading.gif
simpledit/images/mario.png
simpledit/images/olive.svg
simpledit/images/open_file.svg
simpledit/images/pixelate.svg
simpledit/images/redo.svg
simpledit/images/redwood.svg
simpledit/images/remove.svg
simpledit/images/rotate_left.svg
simpledit/images/rotate_right.svg
simpledit/images/saturation.svg
simpledit/images/save_file.svg
simpledit/images/sepia.svg
simpledit/images/smooth.svg
simpledit/images/swirl.svg
simpledit/images/transparency.svg
simpledit/images/triangle.png
simpledit/images/undo.svg
simpledit/images/yellow_tint.svg
simpledit/styling/style.qss
simpledit-1.0.4.data/scripts/SimplEdit
simpledit-1.0.4.dist-info/LICENSE
simpledit-1.0.4.dist-info/METADATA
simpledit-1.0.4.dist-info/WHEEL
simpledit-1.0.4.dist-info/top_level.txt
simpledit-1.0.4.dist-info/RECORD
