Metadata-Version: 2.1
Name: simpledit
Version: 1.0.4
Summary: UNKNOWN
Home-page: https://gitlab.com/torresed/simpledit
Author: Programmers
Author-email: noreply@ufl.edu
License: GPL3
Platform: UNKNOWN
Requires-Dist: Pillow
Requires-Dist: PyQt5
Requires-Dist: PyQt5-sip
Requires-Dist: numpy
Requires-Dist: scikit-image
